{
  "$schema": "https://developer.microsoft.com/json-schemas/fabric/item/report/definition/page/2.0.0/schema.json",
  "name": "4f13d2c0032890252e59",
  "displayName": "Overview",
  "displayOption": "FitToPage",
  "height": 720,
  "width": 1280,
  "filterConfig": {
    "filters": [
      {
        "name": "8272132b1645176e68eb",
        "field": {
          "Column": {
            "Expression": {
              "SourceRef": {
                "Entity": "Lead Time Events"
              }
            },
            "Property": "Lead Time Event"
          }
        },
        "type": "Categorical",
        "filter": {
          "Version": 2,
          "From": [
            {
              "Name": "l",
              "Entity": "Lead Time Events",
              "Type": 0
            }
          ],
          "Where": [
            {
              "Condition": {
                "In": {
                  "Expressions": [
                    {
                      "Column": {
                        "Expression": {
                          "SourceRef": {
                            "Source": "l"
                          }
                        },
                        "Property": "Lead Time Event"
                      }
                    }
                  ],
                  "Values": [
                    [
                      {
                        "Literal": {
                          "Value": "'[ATA Date] to [Inbound Confirmation Date]'"
                        }
                      }
                    ],
                    [
                      {
                        "Literal": {
                          "Value": "'[ATA Date] to [TMS Empty Return Date]'"
                        }
                      }
                    ],
                    [
                      {
                        "Literal": {
                          "Value": "'[ATA Date] to [Unloading Date]'"
                        }
                      }
                    ],
                    [
                      {
                        "Literal": {
                          "Value": "'[MainHub Drop Off] to [MainHub Pickup Date]'"
                        }
                      }
                    ],
                    [
                      {
                        "Literal": {
                          "Value": "'[TMS Full Drop Off Date] to [Unloading Date]'"
                        }
                      }
                    ],
                    [
                      {
                        "Literal": {
                          "Value": "'[Unloading Date] to [TMS Empty Return Date]'"
                        }
                      }
                    ]
                  ]
                }
              }
            }
          ]
        },
        "howCreated": "User",
        "isHiddenInViewMode": true
      }
    ]
  },
  "objects": {
    "outspacePane": [
      {
        "properties": {
          "width": {
            "expr": {
              "Literal": {
                "Value": "316L"
              }
            }
          }
        }
      }
    ]
  }
}